uv_upgrade/__init__.py
uv_upgrade/__main__.py
uv_upgrade-0.2.1.2.dist-info/METADATA
uv_upgrade-0.2.1.2.dist-info/WHEEL
uv_upgrade-0.2.1.2.dist-info/entry_points.txt
uv_upgrade-0.2.1.2.dist-info/RECORD
