Metadata-Version: 2.4
Name: uv-upgrade
Version: 0.2.1.2
Summary: Upgrade dependencies in an UV Project
Author-email: "Kalle M. Aagaard" <km@conscia.com>
Requires-Python: >=3.13
Requires-Dist: rich>=13.9.4
Requires-Dist: typer>=0.15.2; python_full_version >= '3.6'
